Workbook

Sheet Executive Dashboard
B2: Executive Dashboard | L2: Month | M2: Net Worth | N2: Month | O2: Savings | P2: Category | Q2: Amount | S2: Goal | T2: Progress
L3: ='Net Worth'!A9 -> 46174 | M3: ='Net Worth'!J9 -> 7760 | N3: ='Net Worth'!A9 -> 46174 | O3: ='Net Worth'!B9 -> 8000 | P3: Family Support | Q3: ='Monthly Budget'!C12 -> 400 | S3: ='Goals & FIRE'!A5 -> Clear GH₵240 loan | T3: ='Goals & FIRE'!D5 -> 0
L4: ='Net Worth'!A10 -> 46204 | M4: ='Net Worth'!J10 -> 9760 | N4: ='Net Worth'!A10 -> 46204 | O4: ='Net Worth'!B10 -> 9760 | P4: Tithe | Q4: ='Monthly Budget'!C13 -> 300 | S4: ='Goals & FIRE'!A6 -> Reach GH₵10,000 savings | T4: ='Goals & FIRE'!D6 -> 0.8
B5: CURRENT SAVINGS | D5: NET WORTH | F5: SAVINGS RATE | H5: SAVED THIS MONTH | L5: ='Net Worth'!A11 -> 46235 | M5: ='Net Worth'!J11 -> 11760 | N5: ='Net Worth'!A11 -> 46235 | O5: ='Net Worth'!B11 -> 11760 | P5: Personal | Q5: ='Monthly Budget'!C14 -> 100 | S5: ='Goals & FIRE'!A7 -> Reach GH₵20,000 savings | T5: ='Goals & FIRE'!D7 -> 0.4
B6: ='Net Worth'!B9 -> 8000 | D6: ='Net Worth'!J9 -> 7760 | F6: ='Monthly Budget'!C28 -> 0.71428571 | H6: ='Monthly Budget'!C24 -> 2000 | L6: ='Net Worth'!A12 -> 46266 | M6: ='Net Worth'!J12 -> 13760 | N6: ='Net Worth'!A12 -> 46266 | O6: ='Net Worth'!B12 -> 13760 | P6: Other | Q6: =SUM('Monthly Budget'!C15:C19) -> 0 | S6: ='Goals & FIRE'!A8 -> Build 6-month emergency fund | T6: ='Goals & FIRE'!D8 -> 1
L7: ='Net Worth'!A13 -> 46296 | M7: ='Net Worth'!J13 -> 15760 | N7: ='Net Worth'!A13 -> 46296 | O7: ='Net Worth'!B13 -> 15760 | S7: ='Goals & FIRE'!A9 -> Net worth GH₵20,000 by Dec 2026 | T7: ='Goals & FIRE'!D9 -> 0.388
B8: DEBT REMAINING | D8: EMERGENCY FUND | F8: CONTRACT COUNTDOWN | H8: DEC 2026 NET WORTH | L8: ='Net Worth'!A14 -> 46327 | M8: ='Net Worth'!J14 -> 17760 | N8: ='Net Worth'!A14 -> 46327 | O8: ='Net Worth'!B14 -> 17760
B9: ='Net Worth'!C6 -> 240 | D9: ='Contract & Runway'!C16 -> 10 | F9: ='Contract & Runway'!C8 -> 5 | H9: ='Net Worth'!J15 -> 19760 | L9: ='Net Worth'!A15 -> 46357 | M9: ='Net Worth'!J15 -> 19760 | N9: ='Net Worth'!A15 -> 46357 | O9: ='Net Worth'!B15 -> 19760

Sheet Budget Dashboard
T1: Income (chart)
B2: Budget Dashboard | T2: =B13 -> Salary | U2: =C13 -> 2800
B3: Personal finance — income, expenses & savings (GH₵) | T3: =B14 -> Other Income | U3: =C14 -> 0
T4: =B15 -> 0 | U4: =C15 -> 0
B5: Select Month ▼ | D5: Period Compl. | F5: Period Tracking Balance | I5: Period Savings Rate | N5: Year | O5: =TEXT('Monthly Budget'!$B$4,"yyyy") -> 2026
B6: 46174 | D6: =IFERROR('Monthly Budget'!C9/'Monthly Budget'!B9,0) -> 1 | F6: ='Monthly Budget'!C27 -> 0 | I6: ="You are saving "&TEXT('Monthly Budget'!C28,"0.0%")&" of your income" -> You are saving 71.4% of your income | N6: Period | O6: =TEXT('Monthly Budget'!$B$4,"mmmm") -> June | T6: Expenses (chart)
F7: tracked income left to be allocated | T7: =B19 -> Family Support | U7: =C19 -> 400
T8: =B20 -> Tithe | U8: =C20 -> 300
T9: =B21 -> Personal Spending | U9: =C21 -> 100
B10: ="Breakdown — "&TEXT('Monthly Budget'!$B$4,"mmmm yyyy") -> Breakdown — June 2026 | I10: ="Summary — "&TEXT('Monthly Budget'!$B$4,"mmmm yyyy") -> Summary — June 2026 | T10: =B22 -> Transport | U10: =C22 -> 0
T11: =B23 -> Food | U11: =C23 -> 0
B12: Income | C12: Tracked | D12: Budget | E12: % Compl. | F12: Remaining | G12: Excess | T12: Other | U12: =SUM(C24:C27) -> 0
B13: Salary | C13: ='Monthly Budget'!C7 -> 2800 | D13: ='Monthly Budget'!B7 -> 2800 | E13: =IFERROR(C13/D13,"") -> 1 | F13: =MAX(D13-C13,0) -> 0 | G13: =MAX(C13-D13,0) -> 0
B14: Other Income | C14: ='Monthly Budget'!C8 -> 0 | D14: ='Monthly Budget'!B8 -> 0 | E14: =IFERROR(C14/D14,"") | F14: =MAX(D14-C14,0) -> 0 | G14: =MAX(C14-D14,0) -> 0 | T14: Savings (chart)
T15: =B31 -> Savings Transfer | U15: =C31 -> 2000
B16: Total | C16: =SUM(C13:C15) -> 2800 | D16: =SUM(D13:D15) -> 2800 | E16: =C16/D16 -> 1 | F16: =SUM(F13:F15) -> 0 | G16: =SUM(G13:G15) -> 0 | T16: =B32 -> 0 | U16: =C32 -> 0
T17: =B33 -> 0 | U17: =C33 -> 0
B18: Expenses | C18: Tracked | D18: Budget | E18: % Compl. | F18: Remaining | G18: Excess | T18: =B34 -> 0 | U18: =C34 -> 0
B19: Family Support | C19: ='Monthly Budget'!C12 -> 400 | D19: ='Monthly Budget'!B12 -> 400 | E19: =IFERROR(C19/D19,"") -> 1 | F19: =MAX(D19-C19,0) -> 0 | G19: =MAX(C19-D19,0) -> 0
B20: Tithe | C20: ='Monthly Budget'!C13 -> 300 | D20: ='Monthly Budget'!B13 -> 300 | E20: =IFERROR(C20/D20,"") -> 1 | F20: =MAX(D20-C20,0) -> 0 | G20: =MAX(C20-D20,0) -> 0 | T20: Month | U20: Budget | V20: Income | W20: Expenses | X20: Savings
B21: Personal Spending | C21: ='Monthly Budget'!C14 -> 100 | D21: ='Monthly Budget'!B14 -> 100 | E21: =IFERROR(C21/D21,"") -> 1 | F21: =MAX(D21-C21,0) -> 0 | G21: =MAX(C21-D21,0) -> 0 | T21: Jan | U21: ='Monthly Budget'!$B$9 -> 2800 | V21: ='Monthly Budget'!$B$9 -> 2800 | W21: ='Monthly Budget'!$B$20 -> 800 | X21: ='Monthly Budget'!$B$24 -> 2000
B22: Transport | C22: ='Monthly Budget'!C15 -> 0 | D22: ='Monthly Budget'!B15 -> 0 | E22: =IFERROR(C22/D22,"") | F22: =MAX(D22-C22,0) -> 0 | G22: =MAX(C22-D22,0) -> 0 | T22: Feb | U22: ='Monthly Budget'!$B$9 -> 2800 | V22: ='Monthly Budget'!$B$9 -> 2800 | W22: ='Monthly Budget'!$B$20 -> 800 | X22: ='Monthly Budget'!$B$24 -> 2000
B23: Food | C23: ='Monthly Budget'!C16 -> 0 | D23: ='Monthly Budget'!B16 -> 0 | E23: =IFERROR(C23/D23,"") | F23: =MAX(D23-C23,0) -> 0 | G23: =MAX(C23-D23,0) -> 0 | T23: Mar | U23: ='Monthly Budget'!$B$9 -> 2800 | V23: ='Monthly Budget'!$B$9 -> 2800 | W23: ='Monthly Budget'!$B$20 -> 800 | X23: ='Monthly Budget'!$B$24 -> 2000
B24: Health | C24: ='Monthly Budget'!C17 -> 0 | D24: ='Monthly Budget'!B17 -> 0 | E24: =IFERROR(C24/D24,"") | F24: =MAX(D24-C24,0) -> 0 | G24: =MAX(C24-D24,0) -> 0 | T24: Apr | U24: ='Monthly Budget'!$B$9 -> 2800 | V24: ='Monthly Budget'!$B$9 -> 2800 | W24: ='Monthly Budget'!$B$20 -> 800 | X24: ='Monthly Budget'!$B$24 -> 2000
B25: Gifts | C25: ='Monthly Budget'!C18 -> 0 | D25: ='Monthly Budget'!B18 -> 0 | E25: =IFERROR(C25/D25,"") | F25: =MAX(D25-C25,0) -> 0 | G25: =MAX(C25-D25,0) -> 0 | T25: May | U25: ='Monthly Budget'!$B$9 -> 2800 | V25: ='Monthly Budget'!$B$9 -> 2800 | W25: ='Monthly Budget'!$B$20 -> 800 | X25: ='Monthly Budget'!$B$24 -> 2000
B26: Other | C26: ='Monthly Budget'!C19 -> 0 | D26: ='Monthly Budget'!B19 -> 0 | E26: =IFERROR(C26/D26,"") | F26: =MAX(D26-C26,0) -> 0 | G26: =MAX(C26-D26,0) -> 0 | T26: Jun | U26: ='Monthly Budget'!$B$9 -> 2800 | V26: ='Monthly Budget'!C9 -> 2800 | W26: ='Monthly Budget'!C20 -> 800 | X26: ='Monthly Budget'!C24 -> 2000
T27: Jul | U27: ='Monthly Budget'!$B$9 -> 2800 | V27: ='Monthly Budget'!$B$9 -> 2800 | W27: ='Monthly Budget'!$B$20 -> 800 | X27: ='Monthly Budget'!$B$24 -> 2000
B28: Total | C28: =SUM(C19:C27) -> 800 | D28: =SUM(D19:D27) -> 800 | E28: =C28/D28 -> 1 | F28: =SUM(F19:F27) -> 0 | G28: =SUM(G19:G27) -> 0 | T28: Aug | U28: ='Monthly Budget'!$B$9 -> 2800 | V28: ='Monthly Budget'!$B$9 -> 2800 | W28: ='Monthly Budget'!$B$20 -> 800 | X28: ='Monthly Budget'!$B$24 -> 2000
T29: Sep | U29: ='Monthly Budget'!$B$9 -> 2800 | V29: ='Monthly Budget'!$B$9 -> 2800 | W29: ='Monthly Budget'!$B$20 -> 800 | X29: ='Monthly Budget'!$B$24 -> 2000
B30: Savings | C30: Tracked | D30: Budget | E30: % Compl. | F30: Remaining | G30: Excess | T30: Oct | U30: ='Monthly Budget'!$B$9 -> 2800 | V30: ='Monthly Budget'!$B$9 -> 2800 | W30: ='Monthly Budget'!$B$20 -> 800 | X30: ='Monthly Budget'!$B$24 -> 2000
B31: Savings Transfer | C31: ='Monthly Budget'!C23 -> 2000 | D31: ='Monthly Budget'!B23 -> 2000 | E31: =IFERROR(C31/D31,"") -> 1 | F31: =MAX(D31-C31,0) -> 0 | G31: =MAX(C31-D31,0) -> 0 | T31: Nov | U31: ='Monthly Budget'!$B$9 -> 2800 | V31: ='Monthly Budget'!$B$9 -> 2800 | W31: ='Monthly Budget'!$B$20 -> 800 | X31: ='Monthly Budget'!$B$24 -> 2000
T32: Dec | U32: ='Monthly Budget'!$B$9 -> 2800 | V32: ='Monthly Budget'!$B$9 -> 2800 | W32: ='Monthly Budget'!$B$20 -> 800 | X32: ='Monthly Budget'!$B$24 -> 2000
B36: Total | C36: =SUM(C31:C35) -> 2000 | D36: =SUM(D31:D35) -> 2000 | E36: =C36/D36 -> 1 | F36: =SUM(F31:F35) -> 0 | G36: =SUM(G31:G35) -> 0

Sheet Monthly Budget
A1: Monthly Budget
A2: Budget vs actual — actuals pull automatically from the Transactions sheet.
A4: Month | B4: ='Budget Dashboard'!B6 -> 46174 | F4: 2026 Monthly Trend — auto-fills as you log transactions (nothing resets)
F5: Month | G5: Income | H5: Expenses | I5: Savings | J5: Net | K5: Save %
A6: INCOME | B6: Budget | C6: Actual | D6: Variance | F6: =DATE(YEAR($B$4),1,1) -> 46023 | G6: =SUMIFS(Transactions[Amount],Transactions[Type],"Income",Transactions[Date],">="&F6,Transactions[Date],"<="&EOMONTH(F6,0)) -> 0 | H6: =SUMIFS(Transactions[Amount],Transactions[Type],"Expense",Transactions[Date],">="&F6,Transactions[Date],"<="&EOMONTH(F6,0)) -> 0 | I6: =SUMIFS(Transactions[Amount],Transactions[Type],"Savings",Transactions[Date],">="&F6,Transactions[Date],"<="&EOMONTH(F6,0)) -> 0 | J6: =G6-H6-I6 -> 0 | K6: =IFERROR(I6/G6,0) -> 0
A7: Salary | B7: 2800 | C7: =SUMIFS(Transactions[Amount],Transactions[Category],A7,Transactions[Date],">="&$B$4,Transactions[Date],"<="&EOMONTH($B$4,0)) -> 2800 | D7: =C7-B7 -> 0 | F7: =EDATE(F6,1) -> 46054 | G7: =SUMIFS(Transactions[Amount],Transactions[Type],"Income",Transactions[Date],">="&F7,Transactions[Date],"<="&EOMONTH(F7,0)) -> 0 | H7: =SUMIFS(Transactions[Amount],Transactions[Type],"Expense",Transactions[Date],">="&F7,Transactions[Date],"<="&EOMONTH(F7,0)) -> 0 | I7: =SUMIFS(Transactions[Amount],Transactions[Type],"Savings",Transactions[Date],">="&F7,Transactions[Date],"<="&EOMONTH(F7,0)) -> 0 | J7: =G7-H7-I7 -> 0 | K7: =IFERROR(I7/G7,0) -> 0
A8: Other Income | B8: 0 | C8: =SUMIFS(Transactions[Amount],Transactions[Category],A8,Transactions[Date],">="&$B$4,Transactions[Date],"<="&EOMONTH($B$4,0)) -> 0 | D8: =C8-B8 -> 0 | F8: =EDATE(F7,1) -> 46082 | G8: =SUMIFS(Transactions[Amount],Transactions[Type],"Income",Transactions[Date],">="&F8,Transactions[Date],"<="&EOMONTH(F8,0)) -> 0 | H8: =SUMIFS(Transactions[Amount],Transactions[Type],"Expense",Transactions[Date],">="&F8,Transactions[Date],"<="&EOMONTH(F8,0)) -> 0 | I8: =SUMIFS(Transactions[Amount],Transactions[Type],"Savings",Transactions[Date],">="&F8,Transactions[Date],"<="&EOMONTH(F8,0)) -> 0 | J8: =G8-H8-I8 -> 0 | K8: =IFERROR(I8/G8,0) -> 0
A9: Total Income | B9: =SUM(B7:B8) -> 2800 | C9: =SUM(C7:C8) -> 2800 | D9: =C9-B9 -> 0 | F9: =EDATE(F8,1) -> 46113 | G9: =SUMIFS(Transactions[Amount],Transactions[Type],"Income",Transactions[Date],">="&F9,Transactions[Date],"<="&EOMONTH(F9,0)) -> 0 | H9: =SUMIFS(Transactions[Amount],Transactions[Type],"Expense",Transactions[Date],">="&F9,Transactions[Date],"<="&EOMONTH(F9,0)) -> 0 | I9: =SUMIFS(Transactions[Amount],Transactions[Type],"Savings",Transactions[Date],">="&F9,Transactions[Date],"<="&EOMONTH(F9,0)) -> 0 | J9: =G9-H9-I9 -> 0 | K9: =IFERROR(I9/G9,0) -> 0
F10: =EDATE(F9,1) -> 46143 | G10: =SUMIFS(Transactions[Amount],Transactions[Type],"Income",Transactions[Date],">="&F10,Transactions[Date],"<="&EOMONTH(F10,0)) -> 0 | H10: =SUMIFS(Transactions[Amount],Transactions[Type],"Expense",Transactions[Date],">="&F10,Transactions[Date],"<="&EOMONTH(F10,0)) -> 0 | I10: =SUMIFS(Transactions[Amount],Transactions[Type],"Savings",Transactions[Date],">="&F10,Transactions[Date],"<="&EOMONTH(F10,0)) -> 0 | J10: =G10-H10-I10 -> 0 | K10: =IFERROR(I10/G10,0) -> 0
A11: EXPENSES | B11: Budget | C11: Actual | D11: Remaining | F11: =EDATE(F10,1) -> 46174 | G11: =SUMIFS(Transactions[Amount],Transactions[Type],"Income",Transactions[Date],">="&F11,Transactions[Date],"<="&EOMONTH(F11,0)) -> 2800 | H11: =SUMIFS(Transactions[Amount],Transactions[Type],"Expense",Transactions[Date],">="&F11,Transactions[Date],"<="&EOMONTH(F11,0)) -> 800 | I11: =SUMIFS(Transactions[Amount],Transactions[Type],"Savings",Transactions[Date],">="&F11,Transactions[Date],"<="&EOMONTH(F11,0)) -> 2000 | J11: =G11-H11-I11 -> 0 | K11: =IFERROR(I11/G11,0) -> 0.71428571
A12: Family Support | B12: 400 | C12: =SUMIFS(Transactions[Amount],Transactions[Category],A12,Transactions[Date],">="&$B$4,Transactions[Date],"<="&EOMONTH($B$4,0)) -> 400 | D12: =B12-C12 -> 0 | F12: =EDATE(F11,1) -> 46204 | G12: =SUMIFS(Transactions[Amount],Transactions[Type],"Income",Transactions[Date],">="&F12,Transactions[Date],"<="&EOMONTH(F12,0)) -> 0 | H12: =SUMIFS(Transactions[Amount],Transactions[Type],"Expense",Transactions[Date],">="&F12,Transactions[Date],"<="&EOMONTH(F12,0)) -> 0 | I12: =SUMIFS(Transactions[Amount],Transactions[Type],"Savings",Transactions[Date],">="&F12,Transactions[Date],"<="&EOMONTH(F12,0)) -> 0 | J12: =G12-H12-I12 -> 0 | K12: =IFERROR(I12/G12,0) -> 0
A13: Tithe | B13: 300 | C13: =SUMIFS(Transactions[Amount],Transactions[Category],A13,Transactions[Date],">="&$B$4,Transactions[Date],"<="&EOMONTH($B$4,0)) -> 300 | D13: =B13-C13 -> 0 | F13: =EDATE(F12,1) -> 46235 | G13: =SUMIFS(Transactions[Amount],Transactions[Type],"Income",Transactions[Date],">="&F13,Transactions[Date],"<="&EOMONTH(F13,0)) -> 0 | H13: =SUMIFS(Transactions[Amount],Transactions[Type],"Expense",Transactions[Date],">="&F13,Transactions[Date],"<="&EOMONTH(F13,0)) -> 0 | I13: =SUMIFS(Transactions[Amount],Transactions[Type],"Savings",Transactions[Date],">="&F13,Transactions[Date],"<="&EOMONTH(F13,0)) -> 0 | J13: =G13-H13-I13 -> 0 | K13: =IFERROR(I13/G13,0) -> 0
A14: Personal Spending | B14: 100 | C14: =SUMIFS(Transactions[Amount],Transactions[Category],A14,Transactions[Date],">="&$B$4,Transactions[Date],"<="&EOMONTH($B$4,0)) -> 100 | D14: =B14-C14 -> 0 | F14: =EDATE(F13,1) -> 46266 | G14: =SUMIFS(Transactions[Amount],Transactions[Type],"Income",Transactions[Date],">="&F14,Transactions[Date],"<="&EOMONTH(F14,0)) -> 0 | H14: =SUMIFS(Transactions[Amount],Transactions[Type],"Expense",Transactions[Date],">="&F14,Transactions[Date],"<="&EOMONTH(F14,0)) -> 0 | I14: =SUMIFS(Transactions[Amount],Transactions[Type],"Savings",Transactions[Date],">="&F14,Transactions[Date],"<="&EOMONTH(F14,0)) -> 0 | J14: =G14-H14-I14 -> 0 | K14: =IFERROR(I14/G14,0) -> 0
A15: Transport | B15: 0 | C15: =SUMIFS(Transactions[Amount],Transactions[Category],A15,Transactions[Date],">="&$B$4,Transactions[Date],"<="&EOMONTH($B$4,0)) -> 0 | D15: =B15-C15 -> 0 | F15: =EDATE(F14,1) -> 46296 | G15: =SUMIFS(Transactions[Amount],Transactions[Type],"Income",Transactions[Date],">="&F15,Transactions[Date],"<="&EOMONTH(F15,0)) -> 0 | H15: =SUMIFS(Transactions[Amount],Transactions[Type],"Expense",Transactions[Date],">="&F15,Transactions[Date],"<="&EOMONTH(F15,0)) -> 0 | I15: =SUMIFS(Transactions[Amount],Transactions[Type],"Savings",Transactions[Date],">="&F15,Transactions[Date],"<="&EOMONTH(F15,0)) -> 0 | J15: =G15-H15-I15 -> 0 | K15: =IFERROR(I15/G15,0) -> 0
A16: Food | B16: 0 | C16: =SUMIFS(Transactions[Amount],Transactions[Category],A16,Transactions[Date],">="&$B$4,Transactions[Date],"<="&EOMONTH($B$4,0)) -> 0 | D16: =B16-C16 -> 0 | F16: =EDATE(F15,1) -> 46327 | G16: =SUMIFS(Transactions[Amount],Transactions[Type],"Income",Transactions[Date],">="&F16,Transactions[Date],"<="&EOMONTH(F16,0)) -> 0 | H16: =SUMIFS(Transactions[Amount],Transactions[Type],"Expense",Transactions[Date],">="&F16,Transactions[Date],"<="&EOMONTH(F16,0)) -> 0 | I16: =SUMIFS(Transactions[Amount],Transactions[Type],"Savings",Transactions[Date],">="&F16,Transactions[Date],"<="&EOMONTH(F16,0)) -> 0 | J16: =G16-H16-I16 -> 0 | K16: =IFERROR(I16/G16,0) -> 0
A17: Health | B17: 0 | C17: =SUMIFS(Transactions[Amount],Transactions[Category],A17,Transactions[Date],">="&$B$4,Transactions[Date],"<="&EOMONTH($B$4,0)) -> 0 | D17: =B17-C17 -> 0 | F17: =EDATE(F16,1) -> 46357 | G17: =SUMIFS(Transactions[Amount],Transactions[Type],"Income",Transactions[Date],">="&F17,Transactions[Date],"<="&EOMONTH(F17,0)) -> 0 | H17: =SUMIFS(Transactions[Amount],Transactions[Type],"Expense",Transactions[Date],">="&F17,Transactions[Date],"<="&EOMONTH(F17,0)) -> 0 | I17: =SUMIFS(Transactions[Amount],Transactions[Type],"Savings",Transactions[Date],">="&F17,Transactions[Date],"<="&EOMONTH(F17,0)) -> 0 | J17: =G17-H17-I17 -> 0 | K17: =IFERROR(I17/G17,0) -> 0
A18: Gifts | B18: 0 | C18: =SUMIFS(Transactions[Amount],Transactions[Category],A18,Transactions[Date],">="&$B$4,Transactions[Date],"<="&EOMONTH($B$4,0)) -> 0 | D18: =B18-C18 -> 0
A19: Other | B19: 0 | C19: =SUMIFS(Transactions[Amount],Transactions[Category],A19,Transactions[Date],">="&$B$4,Transactions[Date],"<="&EOMONTH($B$4,0)) -> 0 | D19: =B19-C19 -> 0
A20: Total Expenses | B20: =SUM(B12:B19) -> 800 | C20: =SUM(C12:C19) -> 800 | D20: =B20-C20 -> 0
A22: SAVINGS | B22: Budget | C22: Actual | D22: Variance
A23: Savings Transfer | B23: 2000 | C23: =SUMIFS(Transactions[Amount],Transactions[Category],A23,Transactions[Date],">="&$B$4,Transactions[Date],"<="&EOMONTH($B$4,0)) -> 2000 | D23: =C23-B23 -> 0
A24: Total Savings | B24: =SUM(B23:B23) -> 2000 | C24: =SUM(C23:C23) -> 2000 | D24: =C24-B24 -> 0
A26: SUMMARY
A27: Net Cash Flow (unallocated) | C27: =C9-C20-C24 -> 0
A28: Savings Rate | C28: =IFERROR(C24/C9,0) -> 0.71428571
A29: Savings Goal | C29: 2000
A30: Goal Status | C30: =IF(C24>=C29,"✅ On Track","⚠ Behind by "&TEXT(C29-C24,"""GH₵""#,##0")) -> ✅ On Track

Sheet Net Worth
A1: Net Worth
A2: Monthly snapshots. Blue cells are assumptions; overwrite projected months with actual balances as they come.
A4: Planned monthly net savings (Budget: Income − Expenses) | C4: ='Monthly Budget'!B9-'Monthly Budget'!B20 -> 2000
A5: Starting bank balance | C5: 8000
A6: Current loan balance | C6: 240 | L6: Planned vs Actual Net Worth
L7: Actual auto-fills as you log transactions; future months show as gaps.
A8: Month | B8: Bank | C8: Cash | D8: Investments | E8: Other Assets | F8: Total Assets | G8: Loan | H8: Other Debts | I8: Total Liab. | J8: Net Worth | L8: Month | M8: Planned Net Worth | N8: Actual Net Worth | O8: Variance (Act − Plan)
A9: 46174 | B9: =$C$5 -> 8000 | C9: 0 | D9: 0 | E9: 0 | F9: =SUM(B9:E9) -> 8000 | G9: =$C$6 -> 240 | H9: 0 | I9: =SUM(G9:H9) -> 240 | J9: =F9-I9 -> 7760 | L9: =A9 -> 46174 | M9: =J9 -> 7760 | N9: =IF(A9<=EOMONTH(TODAY(),0),$J$9+SUMIFS(Transactions[Amount],Transactions[Type],"Income",Transactions[Date],">"&EOMONTH($A$9,0),Transactions[Date],"<="&EOMONTH(A9,0))-SUMIFS(Transactions[Amount],Transactions[Type],"Expense",Transactions[Date],">"&EOMONTH($A$9,0),Transactions[Date],"<="&EOMONTH(A9,0)),NA()) -> 7760 | O9: =IF(ISNUMBER(N9),N9-M9,"") -> 0
A10: =EDATE(A9,1) -> 46204 | B10: =B9+$C$4-$C$6 -> 9760 | C10: 0 | D10: 0 | E10: 0 | F10: =SUM(B10:E10) -> 9760 | G10: 0 | H10: 0 | I10: =SUM(G10:H10) -> 0 | J10: =F10-I10 -> 9760 | L10: =A10 -> 46204 | M10: =J10 -> 9760 | N10: =IF(A10<=EOMONTH(TODAY(),0),$J$9+SUMIFS(Transactions[Amount],Transactions[Type],"Income",Transactions[Date],">"&EOMONTH($A$9,0),Transactions[Date],"<="&EOMONTH(A10,0))-SUMIFS(Transactions[Amount],Transactions[Type],"Expense",Transactions[Date],">"&EOMONTH($A$9,0),Transactions[Date],"<="&EOMONTH(A10,0)),NA()) -> #N/A | O10: =IF(ISNUMBER(N10),N10-M10,"")
A11: =EDATE(A10,1) -> 46235 | B11: =B10+$C$4 -> 11760 | C11: 0 | D11: 0 | E11: 0 | F11: =SUM(B11:E11) -> 11760 | G11: 0 | H11: 0 | I11: =SUM(G11:H11) -> 0 | J11: =F11-I11 -> 11760 | L11: =A11 -> 46235 | M11: =J11 -> 11760 | N11: =IF(A11<=EOMONTH(TODAY(),0),$J$9+SUMIFS(Transactions[Amount],Transactions[Type],"Income",Transactions[Date],">"&EOMONTH($A$9,0),Transactions[Date],"<="&EOMONTH(A11,0))-SUMIFS(Transactions[Amount],Transactions[Type],"Expense",Transactions[Date],">"&EOMONTH($A$9,0),Transactions[Date],"<="&EOMONTH(A11,0)),NA()) -> #N/A | O11: =IF(ISNUMBER(N11),N11-M11,"")
A12: =EDATE(A11,1) -> 46266 | B12: =B11+$C$4 -> 13760 | C12: 0 | D12: 0 | E12: 0 | F12: =SUM(B12:E12) -> 13760 | G12: 0 | H12: 0 | I12: =SUM(G12:H12) -> 0 | J12: =F12-I12 -> 13760 | L12: =A12 -> 46266 | M12: =J12 -> 13760 | N12: =IF(A12<=EOMONTH(TODAY(),0),$J$9+SUMIFS(Transactions[Amount],Transactions[Type],"Income",Transactions[Date],">"&EOMONTH($A$9,0),Transactions[Date],"<="&EOMONTH(A12,0))-SUMIFS(Transactions[Amount],Transactions[Type],"Expense",Transactions[Date],">"&EOMONTH($A$9,0),Transactions[Date],"<="&EOMONTH(A12,0)),NA()) -> #N/A | O12: =IF(ISNUMBER(N12),N12-M12,"")
A13: =EDATE(A12,1) -> 46296 | B13: =B12+$C$4 -> 15760 | C13: 0 | D13: 0 | E13: 0 | F13: =SUM(B13:E13) -> 15760 | G13: 0 | H13: 0 | I13: =SUM(G13:H13) -> 0 | J13: =F13-I13 -> 15760 | L13: =A13 -> 46296 | M13: =J13 -> 15760 | N13: =IF(A13<=EOMONTH(TODAY(),0),$J$9+SUMIFS(Transactions[Amount],Transactions[Type],"Income",Transactions[Date],">"&EOMONTH($A$9,0),Transactions[Date],"<="&EOMONTH(A13,0))-SUMIFS(Transactions[Amount],Transactions[Type],"Expense",Transactions[Date],">"&EOMONTH($A$9,0),Transactions[Date],"<="&EOMONTH(A13,0)),NA()) -> #N/A | O13: =IF(ISNUMBER(N13),N13-M13,"")
A14: =EDATE(A13,1) -> 46327 | B14: =B13+$C$4 -> 17760 | C14: 0 | D14: 0 | E14: 0 | F14: =SUM(B14:E14) -> 17760 | G14: 0 | H14: 0 | I14: =SUM(G14:H14) -> 0 | J14: =F14-I14 -> 17760 | L14: =A14 -> 46327 | M14: =J14 -> 17760 | N14: =IF(A14<=EOMONTH(TODAY(),0),$J$9+SUMIFS(Transactions[Amount],Transactions[Type],"Income",Transactions[Date],">"&EOMONTH($A$9,0),Transactions[Date],"<="&EOMONTH(A14,0))-SUMIFS(Transactions[Amount],Transactions[Type],"Expense",Transactions[Date],">"&EOMONTH($A$9,0),Transactions[Date],"<="&EOMONTH(A14,0)),NA()) -> #N/A | O14: =IF(ISNUMBER(N14),N14-M14,"")
A15: =EDATE(A14,1) -> 46357 | B15: =B14+$C$4 -> 19760 | C15: 0 | D15: 0 | E15: 0 | F15: =SUM(B15:E15) -> 19760 | G15: 0 | H15: 0 | I15: =SUM(G15:H15) -> 0 | J15: =F15-I15 -> 19760 | L15: =A15 -> 46357 | M15: =J15 -> 19760 | N15: =IF(A15<=EOMONTH(TODAY(),0),$J$9+SUMIFS(Transactions[Amount],Transactions[Type],"Income",Transactions[Date],">"&EOMONTH($A$9,0),Transactions[Date],"<="&EOMONTH(A15,0))-SUMIFS(Transactions[Amount],Transactions[Type],"Expense",Transactions[Date],">"&EOMONTH($A$9,0),Transactions[Date],"<="&EOMONTH(A15,0)),NA()) -> #N/A | O15: =IF(ISNUMBER(N15),N15-M15,"")
A16: =EDATE(A15,1) -> 46388 | B16: =B15+$C$4 -> 21760 | C16: 0 | D16: 0 | E16: 0 | F16: =SUM(B16:E16) -> 21760 | G16: 0 | H16: 0 | I16: =SUM(G16:H16) -> 0 | J16: =F16-I16 -> 21760 | L16: =A16 -> 46388 | M16: =J16 -> 21760 | N16: =IF(A16<=EOMONTH(TODAY(),0),$J$9+SUMIFS(Transactions[Amount],Transactions[Type],"Income",Transactions[Date],">"&EOMONTH($A$9,0),Transactions[Date],"<="&EOMONTH(A16,0))-SUMIFS(Transactions[Amount],Transactions[Type],"Expense",Transactions[Date],">"&EOMONTH($A$9,0),Transactions[Date],"<="&EOMONTH(A16,0)),NA()) -> #N/A | O16: =IF(ISNUMBER(N16),N16-M16,"")
A17: =EDATE(A16,1) -> 46419 | B17: =B16+$C$4 -> 23760 | C17: 0 | D17: 0 | E17: 0 | F17: =SUM(B17:E17) -> 23760 | G17: 0 | H17: 0 | I17: =SUM(G17:H17) -> 0 | J17: =F17-I17 -> 23760 | L17: =A17 -> 46419 | M17: =J17 -> 23760 | N17: =IF(A17<=EOMONTH(TODAY(),0),$J$9+SUMIFS(Transactions[Amount],Transactions[Type],"Income",Transactions[Date],">"&EOMONTH($A$9,0),Transactions[Date],"<="&EOMONTH(A17,0))-SUMIFS(Transactions[Amount],Transactions[Type],"Expense",Transactions[Date],">"&EOMONTH($A$9,0),Transactions[Date],"<="&EOMONTH(A17,0)),NA()) -> #N/A | O17: =IF(ISNUMBER(N17),N17-M17,"")
A18: =EDATE(A17,1) -> 46447 | B18: =B17+$C$4 -> 25760 | C18: 0 | D18: 0 | E18: 0 | F18: =SUM(B18:E18) -> 25760 | G18: 0 | H18: 0 | I18: =SUM(G18:H18) -> 0 | J18: =F18-I18 -> 25760 | L18: =A18 -> 46447 | M18: =J18 -> 25760 | N18: =IF(A18<=EOMONTH(TODAY(),0),$J$9+SUMIFS(Transactions[Amount],Transactions[Type],"Income",Transactions[Date],">"&EOMONTH($A$9,0),Transactions[Date],"<="&EOMONTH(A18,0))-SUMIFS(Transactions[Amount],Transactions[Type],"Expense",Transactions[Date],">"&EOMONTH($A$9,0),Transactions[Date],"<="&EOMONTH(A18,0)),NA()) -> #N/A | O18: =IF(ISNUMBER(N18),N18-M18,"")
A19: =EDATE(A18,1) -> 46478 | B19: =B18+$C$4 -> 27760 | C19: 0 | D19: 0 | E19: 0 | F19: =SUM(B19:E19) -> 27760 | G19: 0 | H19: 0 | I19: =SUM(G19:H19) -> 0 | J19: =F19-I19 -> 27760 | L19: =A19 -> 46478 | M19: =J19 -> 27760 | N19: =IF(A19<=EOMONTH(TODAY(),0),$J$9+SUMIFS(Transactions[Amount],Transactions[Type],"Income",Transactions[Date],">"&EOMONTH($A$9,0),Transactions[Date],"<="&EOMONTH(A19,0))-SUMIFS(Transactions[Amount],Transactions[Type],"Expense",Transactions[Date],">"&EOMONTH($A$9,0),Transactions[Date],"<="&EOMONTH(A19,0)),NA()) -> #N/A | O19: =IF(ISNUMBER(N19),N19-M19,"")
A20: =EDATE(A19,1) -> 46508 | B20: =B19+$C$4 -> 29760 | C20: 0 | D20: 0 | E20: 0 | F20: =SUM(B20:E20) -> 29760 | G20: 0 | H20: 0 | I20: =SUM(G20:H20) -> 0 | J20: =F20-I20 -> 29760 | L20: =A20 -> 46508 | M20: =J20 -> 29760 | N20: =IF(A20<=EOMONTH(TODAY(),0),$J$9+SUMIFS(Transactions[Amount],Transactions[Type],"Income",Transactions[Date],">"&EOMONTH($A$9,0),Transactions[Date],"<="&EOMONTH(A20,0))-SUMIFS(Transactions[Amount],Transactions[Type],"Expense",Transactions[Date],">"&EOMONTH($A$9,0),Transactions[Date],"<="&EOMONTH(A20,0)),NA()) -> #N/A | O20: =IF(ISNUMBER(N20),N20-M20,"")

Sheet Weekly Review
B2: Weekly Finance Review
B3: Every Sunday · 15 minutes · mark a ✓ in each week's column
B5: 15-MINUTE CHECKLIST | C5: Wk 1 | D5: Wk 2 | E5: Wk 3 | F5: Wk 4 | G5: Wk 5
B6: 1. Check bank balances
B7: 2. Review spending
B8: 3. Update net worth
B9: 4. Ensure bills are paid
B10: 5. Invest any excess cash
B13: ASK YOURSELF
B14: • Did I spend on things I value?
B15: • Did I buy anything impulsively?
B16: • Am I moving toward financial freedom?
B18: Notes for this week
B25: “Do not save what is left after spending; spend what is left after saving.” — Warren Buffett

Sheet Principles
B2: Principles & Playbook
B3: Timeless advice from investors who compounded for decades
B5: THE GREAT WEALTH FORMULA
B6: Income × Savings Rate × Time × Good Decisions
B7: Not in the formula: perfect stock picking · getting rich quickly · constant trading
B9: Warren Buffett | D9: John C. Bogle
B10: • Spend less than you earn • Invest consistently • Avoid debt when possible • Buy assets, not status | D10: • Keep fees low • Use broad index funds • Stay invested for decades
B12: Charlie Munger | D12: Morgan Housel
B13: • Avoid stupid mistakes • Be patient • Read constantly • Think long term | D13: • Wealth is what you don't spend • Success is behavior, not intelligence • Flexibility is a financial superpower
B15: Benjamin Graham | D15: Simple Rules That Work
B16: • Protect yourself from emotional decisions • Invest systematically • Focus on value, not hype | D16: • Save at least 20% of income • Build a 6-month emergency fund • Eliminate high-interest debt • Invest automatically every month • Increase investing when income rises • Avoid lifestyle inflation • Think in decades, not months

Sheet Transactions
A1: Transactions
A2: Log every money movement here — the whole workbook reads from this sheet.
A4: Date | B4: Description | C4: Category | D4: Type | E4: Amount | H4: Categories (ref) | I4: Types (ref)
A5: 46174 | B5: Monthly Salary | C5: Salary | D5: Income | E5: 2800 | H5: Salary | I5: Income
A6: 46175 | B6: Family Support | C6: Family Support | D6: Expense | E6: 400 | H6: Family Support | I6: Expense
A7: 46176 | B7: Church Tithe | C7: Tithe | D7: Expense | E7: 300 | H7: Tithe | I7: Transfer
A8: 46178 | B8: Personal Spending | C8: Personal Spending | D8: Expense | E8: 100 | H8: Personal Spending | I8: Investment
A9: 46180 | B9: Transfer to Savings | C9: Savings Transfer | D9: Savings | E9: 2000 | H9: Transport | I9: Savings
H10: Food
H11: Health
H12: Gifts
H13: Loan Payment
H14: Savings Transfer
H15: Other

Sheet Contract & Runway
A1: Contract Runway & Emergency Fund
A2: Your contract ends soon — this is your most important sheet. Blue cells are inputs.
A4: CONTRACT
A5: Contract Start | C5: 46023
A6: Contract End | C6: 46356
A7: Today | C7: =TODAY() -> 46186
A8: Months Remaining | C8: =DATEDIF(TODAY(),C6,"m") -> 5
A9: Current Savings | C9: ='Net Worth'!B9 -> 8000
A10: Monthly Net Savings | C10: ='Net Worth'!C4 -> 2000
A11: Projected Savings at Contract End | C11: =C9+C8*C10 -> 18000
A13: EMERGENCY FUND
A14: Monthly Essential Spending | C14: ='Monthly Budget'!B20 -> 800
A15: Current Emergency Fund (savings) | C15: =C9 -> 8000
A16: Months Survivable Without Income | C16: =IFERROR(C15/C14,0) -> 10
A18: Target | C18: Amount Needed | D18: Funded | E18: Status
A19: 3 months | C19: =3*$C$14 -> 2400 | D19: =IFERROR(MIN(1,$C$15/C19),0) -> 1 | E19: =IF($C$15>=C19,"✅ Funded","⚠ "&TEXT(C19-$C$15,"""GH₵""#,##0")&" to go") -> ✅ Funded
A20: 6 months | C20: =6*$C$14 -> 4800 | D20: =IFERROR(MIN(1,$C$15/C20),0) -> 1 | E20: =IF($C$15>=C20,"✅ Funded","⚠ "&TEXT(C20-$C$15,"""GH₵""#,##0")&" to go") -> ✅ Funded
A21: 12 months | C21: =12*$C$14 -> 9600 | D21: =IFERROR(MIN(1,$C$15/C21),0) -> 0.83333333 | E21: =IF($C$15>=C21,"✅ Funded","⚠ "&TEXT(C21-$C$15,"""GH₵""#,##0")&" to go") -> ⚠ GH₵1,600 to go

Sheet Goals & FIRE
A1: Goals & FIRE
A2: Progress updates automatically from your savings and net worth. Blue cells are yours to update.
A4: GOAL | B4: Target | C4: Current | D4: Progress | E4: Target Date | F4: Status
A5: Clear GH₵240 loan | B5: 240 | C5: =B5-'Net Worth'!C6 -> 0 | D5: =IFERROR(MIN(1,C5/B5),0) -> 0 | E5: 46234 | F5: =IF(D5>=1,"✅ Done","In progress") -> In progress
A6: Reach GH₵10,000 savings | B6: 10000 | C6: ='Net Worth'!B9 -> 8000 | D6: =IFERROR(MIN(1,C6/B6),0) -> 0.8 | E6: 46265 | F6: =IF(D6>=1,"✅ Done","In progress") -> In progress
A7: Reach GH₵20,000 savings | B7: 20000 | C7: ='Net Worth'!B9 -> 8000 | D7: =IFERROR(MIN(1,C7/B7),0) -> 0.4 | E7: 46446 | F7: =IF(D7>=1,"✅ Done","In progress") -> In progress
A8: Build 6-month emergency fund | B8: ='Contract & Runway'!C20 -> 4800 | C8: ='Contract & Runway'!C15 -> 8000 | D8: =IFERROR(MIN(1,C8/B8),0) -> 1 | E8: ='Contract & Runway'!C6 -> 46356 | F8: =IF(D8>=1,"✅ Done","In progress") -> ✅ Done
A9: Net worth GH₵20,000 by Dec 2026 | B9: 20000 | C9: ='Net Worth'!J9 -> 7760 | D9: =IFERROR(MIN(1,C9/B9),0) -> 0.388 | E9: =DATE(2026,12,31) -> 46387 | F9: =IF(D9>=1,"✅ Done","In progress") -> In progress
A11: FINANCIAL INDEPENDENCE (FIRE)
A12: Monthly Essential Spending | C12: ='Monthly Budget'!C20 -> 800
A13: Annual Expenses | C13: =C12*12 -> 9600
A14: FI Multiple (25× = 4% rule) | C14: 25
A15: FI Number (target net worth) | C15: =C13*C14 -> 240000
A16: Current Net Worth | C16: ='Net Worth'!J9 -> 7760
A17: FI Progress | C17: =IFERROR(C16/C15,0) -> 0.032333333
